function_flow/__init__.py
function_flow/cloud_task_helper.py
function_flow/futures.py
function_flow/tasks.py
function_flow-0.0.7.dist-info/METADATA
function_flow-0.0.7.dist-info/WHEEL
function_flow-0.0.7.dist-info/top_level.txt
function_flow-0.0.7.dist-info/RECORD
