Metadata-Version: 2.1
Name: function-flow
Version: 0.0.7
Summary: Function Flow - workflow management on Google Cloud Functions
Author: Chi Zhang
Author-email: chii@google.com
License: Apache
Requires-Python: >=3.6.0
Requires-Dist: google-api-core (>=1.22.1)
Requires-Dist: google-api-python-client (>=1.9.3)
Requires-Dist: google-cloud-core (>=1.4.4)
Requires-Dist: google-cloud-firestore (>=1.6.2)
Requires-Dist: google-cloud-pubsub (>=1.0.2)
Requires-Dist: google-cloud-storage (>=1.38.0)
Requires-Dist: google-cloud-tasks (>=2.0.0)
